README.rst
setup.py
netwell/__init__.py
netwell/checkers.py
netwell/command.py
netwell.egg-info/PKG-INFO
netwell.egg-info/SOURCES.txt
netwell.egg-info/dependency_links.txt
netwell.egg-info/entry_points.txt
netwell.egg-info/requires.txt
netwell.egg-info/top_level.txt