Metadata-Version: 1.1
Name: netwell
Version: 0.2.0
Summary: Checker to determine if all is well
Home-page: http://github.com/pennersr/netwell
Author: Raymond Penners
Author-email: raymond.penners@intenct.nl
License: UNKNOWN
Keywords: network ping check test
Platform: UNKNOWN
Classifier: Development Status :: 3 - Alpha
Classifier: Intended Audience :: Developers
Classifier: Topic :: Software Development :: Libraries :: Python Modules
Classifier: Environment :: Web Environment
Classifier: Topic :: Internet
Classifier: License :: OSI Approved :: MIT License
Classifier: Operating System :: OS Independent
Classifier: Programming Language :: Python
Classifier: Programming Language :: Python :: 3.4
Classifier: Programming Language :: Python :: 3.5
